[{"bundesland":"W","freq":1802,"date":"20200407_140000"},{"bundesland":"Vbg","freq":768,"date":"20200407_140000"},{"bundesland":"T","freq":2829,"date":"20200407_140000"},{"bundesland":"Stmk","freq":1372,"date":"20200407_140000"},{"bundesland":"Sbg","freq":1091,"date":"20200407_140000"},{"bundesland":"OÖ","freq":1987,"date":"20200407_140000"},{"bundesland":"NÖ","freq":2067,"date":"20200407_140000"},{"bundesland":"Ktn","freq":338,"date":"20200407_140000"},{"bundesland":"Bgld","freq":234,"date":"20200407_140000"}]
